{
  "main": {
    "id": "ba238ece98349b5c",
    "type": "split",
    "children": [
      {
        "id": "2ec24a7275139d64",
        "type": "tabs",
        "children": [
          {
            "id": "7fa5759281f5d0e8",
            "type": "leaf",
            "state": {
              "type": "empty",
              "state": {}
            }
          }
        ]
      }
    ],
    "direction": "vertical"
  },
  "left": {
    "id": "5eb6660d2336b10b",
    "type": "split",
    "children": [
      {
        "id": "20568c7377e7d865",
        "type": "tabs",
        "children": [
          {
            "id": "c763575cb748721e",
            "type": "leaf",
            "state": {
              "type": "file-explorer",
              "state": {
                "sortOrder": "alphabetical"
              }
            }
          },
          {
            "id": "d0989b295985b2c1",
            "type": "leaf",
            "state": {
              "type": "search",
              "state": {
                "query": "",
                "matchingCase": false,
                "explainSearch": false,
                "collapseAll": false,
                "extraContext": false,
                "sortOrder": "alphabetical"
              }
            }
          },
          {
            "id": "77ee777e7d3a063d",
            "type": "leaf",
            "state": {
              "type": "tag",
              "state": {
                "sortOrder": "frequency",
                "useHierarchy": true
              }
            }
          }
        ],
        "currentTab": 1
      }
    ],
    "direction": "horizontal",
    "width": 299.5
  },
  "right": {
    "id": "57e2b10c14e61662",
    "type": "split",
    "children": [
      {
        "id": "c9956f8eaa47a6d1",
        "type": "tabs",
        "children": [
          {
            "id": "f962f4cd29a397a3",
            "type": "leaf",
            "state": {
              "type": "graph",
              "state": {}
            }
          }
        ]
      }
    ],
    "direction": "horizontal",
    "width": 387.5
  },
  "left-ribbon": {
    "hiddenItems": {
      "switcher:Меню быстрого перехода": true,
      "graph:Граф": false,
      "canvas:Создать новый холст": false,
      "daily-notes:Сегодняшняя заметка": true,
      "templates:Вставить шаблон": true,
      "command-palette:Открыть палитру команд": true,
      "obsidian-excalidraw-plugin:Create new drawing": true,
      "obsidian-git:Open Git source control": true,
      "homepage:Open homepage": true
    }
  },
  "active": "d0989b295985b2c1",
  "lastOpenFiles": [
    "Innopolis 1st year - Fall Semester.md",
    "Analytical Geometry and Linear Algebra I.md",
    "Vector Algebra.md",
    "Linear dependency, independency. Basis. The Dot product and its properties..md",
    "Indefinite and definite integral.md",
    "Без названия.canvas",
    "References.md",
    "Excalidraw/Drawing 2024-09-08 22.31.24.excalidraw.md",
    "Excalidraw",
    "Без названия 4.canvas",
    "Без названия 3.canvas",
    "Без названия 2.canvas",
    "Без названия 1.canvas",
    "Home/The Beginning.md",
    "Innopolis University.md",
    "Basic of Logic.md",
    "Library/lckBnikLr0k.jpg",
    "Library/Не подтверждено 746170.~",
    "Library/Pasted image 20240908221344.png",
    "Library/448680_The image must be in panorama format with an aspec_xl-1024-v1-0.png",
    "Library/wallpaperflare.com_wallpaper.jpg",
    "Library/illustration-city-anime-painting-wallpaper-thumb.jpg",
    "Library/149632-noch-anime-atmosfera-vselennaya-kosmos-3840x2160.jpg.~tmp",
    "Library/149632-noch-anime-atmosfera-vselennaya-kosmos-3840x2160.jpg",
    "Computer instructions, their representations, and execution.md",
    "Library/Excalidraw/Drawing 2024-09-08 20.32.46.excalidraw.md",
    "Library/Pasted image 20240908203938.png",
    "Library/Math/Analiticheskaya_geometria_i_lineynaya_algebra_2020_Umnov.pdf",
    "Static & Dynamic Typing. C Type System. Pointer Type..md",
    "Library/Excalidraw",
    "templates",
    "projects",
    "periodic/templates",
    "Fundamental Ideas of Computer Architecture.md",
    "Classification of Formulas. Logical Equivalence. Algebraic Normal Form..md",
    "Introduction. Vector Spaces. Linear Independence. Basis..md",
    "Introduction. The C Programming Language..md",
    "Introduction. Foundation. Truth Table. Normal Forms..md",
    "Introduction. About MathAnal. Natural Numbers. Relations, Functions, Operations. Number Systems. Axiomatic approaches..md",
    "The C language.md",
    "periodic/Weekly",
    "periodic/Daily",
    "The C++ language.md",
    "The Java language.md",
    "Theory of limits and continuity.md",
    "The fundamental principles for modern computer systems.md",
    "Set Theory and Finite combinatorics.md",
    "Set of Numbers. Basic of Theory of Sets..md",
    "Excalidraw/Lecture 2 - Theorem 1.png",
    "Library/Photos/Pasted image 20240906181422.png",
    "Library/Photos/Pasted image 20240906180825.png"
  ]
}